{
  "name": "La Redoute",
  "documents": {
    "General Conditions of Sale": {
      "fetch": "https://www.laredoute.fr/help_conditions.aspx",
      "select": [
        ".staticContent"
      ],
      "remove": [
        "#sommaire",
        "a[title=\"imprimer\"]",
        "a[title=\"enregistrer\"]",
        ".retour"
      ],
      "executeClientScripts": true
    },
    "Privacy Policy": {
      "fetch": "https://www.laredoute.fr/espace-mentions_legales.aspx",
      "select": [
        "#Rdte_mentions_content"
      ],
      "executeClientScripts": true
    }
  }
}
